MHDWaveHarmonics/CalcFieldLineVa.py
MHDWaveHarmonics/DipoleField.py
MHDWaveHarmonics/FindHarmonics.py
MHDWaveHarmonics/FitPlasma.py
MHDWaveHarmonics/FitPlasmaToHarmonic.py
MHDWaveHarmonics/GetFieldLine.py
MHDWaveHarmonics/GetSandhuParams.py
MHDWaveHarmonics/Globals.py
MHDWaveHarmonics/PlotFieldLineDensity.py
MHDWaveHarmonics/PlotHarmonics.py
MHDWaveHarmonics/SolveWave.py
MHDWaveHarmonics/__init__.py
MHDWaveHarmonics/__data/libwh/ApproxFundamental.cc
MHDWaveHarmonics/__data/libwh/ApproxFundamental.h
MHDWaveHarmonics/__data/libwh/ArgSort.cc
MHDWaveHarmonics/__data/libwh/ArgSort.h
MHDWaveHarmonics/__data/libwh/Linterp.cc
MHDWaveHarmonics/__data/libwh/Linterp.h
MHDWaveHarmonics/__data/libwh/diff.cc
MHDWaveHarmonics/__data/libwh/diff.h
MHDWaveHarmonics/__data/libwh/findharmonics.cc
MHDWaveHarmonics/__data/libwh/findharmonics.h
MHDWaveHarmonics/__data/libwh/libwh.cc
MHDWaveHarmonics/__data/libwh/libwh.h
MHDWaveHarmonics/__data/libwh/libwh.so
MHDWaveHarmonics/__data/libwh/makefile
MHDWaveHarmonics/__data/libwh/misfitobject.cc
MHDWaveHarmonics/__data/libwh/misfitobject.h
MHDWaveHarmonics/__data/libwh/neldermead.cc
MHDWaveHarmonics/__data/libwh/neldermead.h
MHDWaveHarmonics/__data/libwh/rkg.cc
MHDWaveHarmonics/__data/libwh/rkg.h
MHDWaveHarmonics/__data/libwh/solvewave.cc
MHDWaveHarmonics/__data/libwh/solvewave.h
MHDWaveHarmonics/__data/libwh/spline.cc
MHDWaveHarmonics/__data/libwh/spline.h
MHDWaveHarmonics-0.0.3.dist-info/LICENSE
MHDWaveHarmonics-0.0.3.dist-info/METADATA
MHDWaveHarmonics-0.0.3.dist-info/WHEEL
MHDWaveHarmonics-0.0.3.dist-info/top_level.txt
MHDWaveHarmonics-0.0.3.dist-info/RECORD
