Metadata-Version: 2.1
Name: MHDWaveHarmonics
Version: 0.0.3
Summary: Some simple tools for modelling MHD wave harmonics in an arbitrary magnetic field geometry.
Home-page: https://github.com/mattkjames7/MHDWaveHarmonics
Author: Matthew Knight James
Author-email: mattkjames7@gmail.com
License: UNKNOWN
Platform: UNKNOWN
Classifier: Programming Language :: Python :: 3
Classifier: License :: OSI Approved :: MIT License
Classifier: Operating System :: POSIX
Requires-Dist: numpy
Requires-Dist: scipy
Requires-Dist: matplotlib
Requires-Dist: PyGeopack (>=0.2.7)
Requires-Dist: FieldTracing
